LICENSE.txt
MANIFEST.in
README.md
requirements.txt
setup.cfg
setup.py
adolet_db/__init__.py
adolet_db.egg-info/PKG-INFO
adolet_db.egg-info/SOURCES.txt
adolet_db.egg-info/dependency_links.txt
adolet_db.egg-info/requires.txt
adolet_db.egg-info/top_level.txt
adolet_db/common/__init__.py
adolet_db/common/authenticate_db.py
adolet_db/common/is_args_none.py
adolet_db/repo/__init__.py
adolet_db/repo/adolet_repo.py
adolet_db/repo/cache_postgres_repo.py
adolet_db/repo/postgres_repo.py
tests/__init__.py
tests/test_postgres_repo.py