Metadata-Version: 1.1
Name: adolet-db
Version: 0.1.6
Summary: API for AdoletDB
Home-page: https://github.com/adolet/adolet-db/
Author: Adolet
Author-email: support@adolet.com
License: MIT
Download-URL: https://github.com/adolet/adolet-db/archive/refs/tags/v0.1.6.tar.gz
Keywords: Adolet,Adolet DB,Adolet ORM
Platform: UNKNOWN
Classifier: Development Status :: 3 - Alpha
Classifier: Intended Audience :: Developers
Classifier: Topic :: Software Development :: Build Tools
Classifier: License :: OSI Approved :: MIT License
Classifier: Programming Language :: Python :: 3.8
Classifier: Programming Language :: Python :: 3.9
